{
  "contacts": [
    {
      "first_name": "Katy",
      "second_name": "James",
      "phone": "+991234567820",
      "avatarURL": "https://images.unsplash.com/photo-1534528741775-53994a69daeb?ixlib=rb-4.0.3&ixid=M3wxMjA3fDB8MHxzZWFyY2h8Mzd8fGF2YXRhcnxlbnwwfHwwfHx8MA%3D%3D&auto=format&fit=crop&w=500&q=60",
      "notes": "SEO expert",
      "id": "vZLqyM_"
    },
    {
      "first_name": "Sam",
      "second_name": "Ken",
      "phone": "+14845219731",
      "avatarURL": "https://images.unsplash.com/photo-1633332755192-727a05c4013d?ixlib=rb-4.0.3&ixid=M3wxMjA3fDB8MHxzZWFyY2h8OHx8YXZhdGFyfGVufDB8fDB8fHww&auto=format&fit=crop&w=500&q=60",
      "notes": "Buisness CEO",
      "id": "wu7z0pn"
    },
    {
      "first_name": "Dawit",
      "second_name": "Fikadu",
      "phone": "+251933011745",
      "avatarURL": "https://images.unsplash.com/photo-1630567598693-999d1d740ec8?ixlib=rb-4.0.3&ixid=M3wxMjA3fDB8MHxzZWFyY2h8MzV8fGV0aGlvcGlhbiUyMGF2YXRhcnxlbnwwfHwwfHx8MA%3D%3D&auto=format&fit=crop&w=500&q=60",
      "notes": "Zola pictures",
      "id": "oc0mWOV"
    },
    {
      "first_name": "L",
      "second_name": "L",
      "phone": "+2519999999",
      "avatarURL": "L",
      "notes": "L",
      "id": "2xDj1KF"
    }
  ]
}